<?xml version="1.0" encoding="UTF-8"?>
<PROPERTY-GROUPS xmlns:xsi="http://www.w3.org/2001/XMLSchema-instance">
  <PROPERTY-GROUP isHostBased="false">
    <NAME>genapp (2)</NAME>
    <DESCRIPTION>This property group was automatically generated based on your system definitions.</DESCRIPTION>
    <LAST-EDITED>2022-04-28 16:50:31.518</LAST-EDITED>
    <CATEGORY-INSTANCE>
      <CATEGORY>COBOL_SETTINGS</CATEGORY>
      <PROPERTY>
        <NAME>HOST_COMPILE_OPTIONS</NAME>
        <VALUE></VALUE>
      </PROPERTY>
      <PROPERTY>
        <NAME>HOST_COMPILE_OPTIONS_APPEND</NAME>
        <VALUE>FALSE</VALUE>
      </PROPERTY>
      <PROPERTY>
        <NAME>COMPILE_JCL_PROCEDURE_NAME</NAME>
        <VALUE>ELAXFCOC</VALUE>
      </PROPERTY>
      <PROPERTY>
        <NAME>COMPILE_JOB_STEPS</NAME>
        <VALUE>COBOL,20:</VALUE>
      </PROPERTY>
      <PROPERTY>
        <NAME>LISTING_DATASET</NAME>
        <VALUE></VALUE>
      </PROPERTY>
      <PROPERTY>
        <NAME>OBJECT_DATASET</NAME>
        <VALUE>&lt;HLQ>.COBOBJS.OBJ</VALUE>
      </PROPERTY>
      <PROPERTY>
        <NAME>HOST_SYSLIB</NAME>
        <VALUE>&lt;HLQ>.COBOL.COPYLIB</VALUE>
      </PROPERTY>
      <PROPERTY>
        <NAME>COMPILE_ERROR_FEEDBACK_ENABLED</NAME>
        <VALUE>TRUE</VALUE>
      </PROPERTY>
      <PROPERTY>
        <NAME>ERROR_FEEDBACK_FILE_PREFIX</NAME>
        <VALUE>&lt;HLQ>.ERRCOB</VALUE>
      </PROPERTY>
      <PROPERTY>
        <NAME>COMPILE_ADDITIONAL_JCL</NAME>
        <VALUE>//******* ADDITIONAL JCL FOR COMPILE HERE ******</VALUE>
      </PROPERTY>
      <PROPERTY>
        <NAME>COMPILE_SYSDEBUG_DATASET</NAME>
        <VALUE>&lt;HLQ>.COBOL.SYSDEBUG</VALUE>
      </PROPERTY>
      <PROPERTY>
        <NAME>HOST_USE_CICS</NAME>
        <VALUE>FALSE</VALUE>
      </PROPERTY>
      <PROPERTY>
        <NAME>HOST_CICS_LEVEL</NAME>
        <VALUE>CTS55</VALUE>
      </PROPERTY>
      <PROPERTY>
        <NAME>HOST_CICS_SEPTRANSLATOR</NAME>
        <VALUE>FALSE</VALUE>
      </PROPERTY>
      <PROPERTY>
        <NAME>CICS_TRANSLATOR_JCL_PROCEDURE_NAME</NAME>
        <VALUE>ELAXFCOT</VALUE>
      </PROPERTY>
      <PROPERTY>
        <NAME>CICS_TRANSLATOR_JOB_STEPS</NAME>
        <VALUE>COBTRAN,20:</VALUE>
      </PROPERTY>
      <PROPERTY>
        <NAME>HOST_CICS_OPTIONS</NAME>
        <VALUE></VALUE>
      </PROPERTY>
      <PROPERTY>
        <NAME>HOST_CICS_SYSLIB</NAME>
        <VALUE>SYS1.SDFHCOB</VALUE>
      </PROPERTY>
      <PROPERTY>
        <NAME>HOST_USE_DB2</NAME>
        <VALUE>FALSE</VALUE>
      </PROPERTY>
      <PROPERTY>
        <NAME>HOST_USE_DB2_ROUTINE_DEVELOPMENT</NAME>
        <VALUE xsi:nil="true"/>
      </PROPERTY>
      <PROPERTY>
        <NAME>HOST_USE_DB2_ROUTINE_DEVELOPMENT_SUBSYSTEM_ID</NAME>
        <VALUE xsi:nil="true"/>
      </PROPERTY>
      <PROPERTY>
        <NAME>HOST_DB2_PREPROCESSOR</NAME>
        <VALUE>FALSE</VALUE>
      </PROPERTY>
      <PROPERTY>
        <NAME>HOST_DB2_JCL_PROCEDURE_NAME</NAME>
        <VALUE>ELAXFCOP</VALUE>
      </PROPERTY>
      <PROPERTY>
        <NAME>HOST_DB2_JOB_STEPS</NAME>
        <VALUE>COBPRE,20:</VALUE>
      </PROPERTY>
      <PROPERTY>
        <NAME>HOST_DB2_OPTIONS</NAME>
        <VALUE></VALUE>
      </PROPERTY>
      <PROPERTY>
        <NAME>HOST_DB2_SYSLIB</NAME>
        <VALUE>&lt;HLQ>.DB2.SYSLIB</VALUE>
      </PROPERTY>
      <PROPERTY>
        <NAME>HOST_DB2_DBRMLOCATION</NAME>
        <VALUE>&lt;HLQ>.DB2DBRM</VALUE>
      </PROPERTY>
      <PROPERTY>
        <NAME>HOST_DB2_SYSTSIN</NAME>
        <VALUE>//*UNCOMMENT AND TAILOR THE FOLLOWING CODE IF YOUR SYSTSIN STATEMENT**
//*CONTAINS BIND INSTRUCTIONS:                                                  
//*//SYSTSIN   DD  *                                                            
//* DSN SYSTEM(YOURSUBSYSTEM)
//*    BIND PACKAGE(YOURLOCATION.YOURPACKAGE)-
//*       OWNER(YOURUSERID) -
//*       MEMBER(YOURMEMBER) -
//*       LIBRARY('YOUR.DBRM.LIBRARY') -
//*       ACTION(REP) -
//*       VALIDATE(BIND)
//*     BIND PLAN(YOURPLAN) -
//*       PKLIST(YOURLOCATION.YOURPACKAGENAME.*)
//* END
//*    OR
//*UNCOMMENT AND TAILOR THE FOLLOWING CODE IF YOUR SYSTSIN STATEMENT**
//*POINTS TO A DATA SET CONTAINING BIND INSTRUCTIONS
//*//SYSTSIN DD DSN=USERID.BIND(MEMBER),DISP=SHR
//*</VALUE>
      </PROPERTY>
      <PROPERTY>
        <NAME>HOST_USE_IMS</NAME>
        <VALUE>FALSE</VALUE>
      </PROPERTY>
      <PROPERTY>
        <NAME>HOST_IMS_LIBRARY</NAME>
        <VALUE>&lt;HLQ>.IMS.RESLIB</VALUE>
      </PROPERTY>
      <PROPERTY>
        <NAME>HOST_USER_VARIABLES</NAME>
        <VALUE xsi:nil="true"/>
      </PROPERTY>
      <PROPERTY>
        <NAME>HOST_GLOBAL_VARIABLES</NAME>
        <VALUE xsi:nil="true"/>
      </PROPERTY>
      <PROPERTY>
        <NAME>ADDED_STEP_ADDITIONAL_JCL</NAME>
        <VALUE xsi:nil="true"/>
      </PROPERTY>
      <PROPERTY>
        <NAME>ADDED_STEP_OPTIONS</NAME>
        <VALUE xsi:nil="true"/>
      </PROPERTY>
      <PROPERTY>
        <NAME>ADDED_STEP_ERROR_FEEDBACK</NAME>
        <VALUE xsi:nil="true"/>
      </PROPERTY>
      <PROPERTY>
        <NAME>ADDED_STEP_ERROR_FEEDBACK_FILE_PREFIX</NAME>
        <VALUE xsi:nil="true"/>
      </PROPERTY>
      <PROPERTY>
        <NAME>LOCAL_CICS_PREPROCESSOR</NAME>
        <VALUE xsi:nil="true"/>
      </PROPERTY>
      <PROPERTY>
        <NAME>LOCAL_CICS_PREPROCESSOR_OPTIONS</NAME>
        <VALUE xsi:nil="true"/>
      </PROPERTY>
      <PROPERTY>
        <NAME>LOCAL_COMPILE_OPTIONS</NAME>
        <VALUE>TEST,ADATA,EXIT(ADEXIT(FTTFDBKW))</VALUE>
      </PROPERTY>
      <PROPERTY>
        <NAME>LOCAL_DB2_COPROCESSOR</NAME>
        <VALUE xsi:nil="true"/>
      </PROPERTY>
      <PROPERTY>
        <NAME>LOCAL_DB2_CONNECTION</NAME>
        <VALUE xsi:nil="true"/>
      </PROPERTY>
      <PROPERTY>
        <NAME>LOCAL_DB2_COPROCESSOR_OPTIONS</NAME>
        <VALUE xsi:nil="true"/>
      </PROPERTY>
      <PROPERTY>
        <NAME>LOCAL_SYSLIB</NAME>
        <VALUE xsi:nil="true"/>
      </PROPERTY>
      <PROPERTY>
        <NAME>LOCAL_ENVIRONMENT_VARIABLES</NAME>
        <VALUE xsi:nil="true"/>
      </PROPERTY>
      <PROPERTY>
        <NAME>LOCAL_PREPROCESSOR_DESCRIPTION</NAME>
        <VALUE>-INC/++INCLUDE Preprocessor</VALUE>
      </PROPERTY>
      <PROPERTY>
        <NAME>LOCAL_PREPROCESSOR_NAME</NAME>
        <VALUE>${bundle:com.ibm.systemz.preprocessor.include}\bin\win32\PPINCL01.exe</VALUE>
      </PROPERTY>
      <PROPERTY>
        <NAME>LOCAL_PREPROCESSOR_OPTIONS</NAME>
        <VALUE></VALUE>
      </PROPERTY>
      <PROPERTY>
        <NAME>LOCAL_PREPROCESSOR_OUTPUT_FILE_NAME</NAME>
        <VALUE>${resource_fn}.dk1</VALUE>
      </PROPERTY>
      <PROPERTY>
        <NAME>LOCAL_PREPROCESSOR_SUPPORT_ERRFDBK</NAME>
        <VALUE>TRUE</VALUE>
      </PROPERTY>
      <PROPERTY>
        <NAME>LOCAL_PREPROCESSOR_XML_LOCATION</NAME>
        <VALUE>${resource_fn}_PP1.xml</VALUE>
      </PROPERTY>
      <PROPERTY>
        <NAME>LOCAL_PREPROCESSOR_ENVIRONMENT_VARIABLES</NAME>
        <VALUE>SET SYSLIB=${project_loc}\includes</VALUE>
      </PROPERTY>
      <PROPERTY>
        <NAME>LOCAL_PREPROCESSOR_IS_ACTIVE</NAME>
        <VALUE>FALSE</VALUE>
      </PROPERTY>
      <PROPERTY>
        <NAME>LOCAL_PREPROCESSOR_NUMBER_OF_PPS</NAME>
        <VALUE>1</VALUE>
      </PROPERTY>
      <PROPERTY>
        <NAME>LOCAL_PREPROCESSOR_DESCRIPTION02</NAME>
        <VALUE xsi:nil="true"/>
      </PROPERTY>
      <PROPERTY>
        <NAME>LOCAL_PREPROCESSOR_DESCRIPTION03</NAME>
        <VALUE xsi:nil="true"/>
      </PROPERTY>
      <PROPERTY>
        <NAME>LOCAL_PREPROCESSOR_DESCRIPTION04</NAME>
        <VALUE xsi:nil="true"/>
      </PROPERTY>
      <PROPERTY>
        <NAME>LOCAL_PREPROCESSOR_DESCRIPTION05</NAME>
        <VALUE xsi:nil="true"/>
      </PROPERTY>
      <PROPERTY>
        <NAME>LOCAL_PREPROCESSOR_DESCRIPTION06</NAME>
        <VALUE xsi:nil="true"/>
      </PROPERTY>
      <PROPERTY>
        <NAME>LOCAL_PREPROCESSOR_DESCRIPTION07</NAME>
        <VALUE xsi:nil="true"/>
      </PROPERTY>
      <PROPERTY>
        <NAME>LOCAL_PREPROCESSOR_DESCRIPTION08</NAME>
        <VALUE xsi:nil="true"/>
      </PROPERTY>
      <PROPERTY>
        <NAME>LOCAL_PREPROCESSOR_DESCRIPTION09</NAME>
        <VALUE xsi:nil="true"/>
      </PROPERTY>
      <PROPERTY>
        <NAME>LOCAL_PREPROCESSOR_DESCRIPTION10</NAME>
        <VALUE xsi:nil="true"/>
      </PROPERTY>
      <PROPERTY>
        <NAME>LOCAL_PREPROCESSOR_NAME02</NAME>
        <VALUE xsi:nil="true"/>
      </PROPERTY>
      <PROPERTY>
        <NAME>LOCAL_PREPROCESSOR_NAME03</NAME>
        <VALUE xsi:nil="true"/>
      </PROPERTY>
      <PROPERTY>
        <NAME>LOCAL_PREPROCESSOR_NAME04</NAME>
        <VALUE xsi:nil="true"/>
      </PROPERTY>
      <PROPERTY>
        <NAME>LOCAL_PREPROCESSOR_NAME05</NAME>
        <VALUE xsi:nil="true"/>
      </PROPERTY>
      <PROPERTY>
        <NAME>LOCAL_PREPROCESSOR_NAME06</NAME>
        <VALUE xsi:nil="true"/>
      </PROPERTY>
      <PROPERTY>
        <NAME>LOCAL_PREPROCESSOR_NAME07</NAME>
        <VALUE xsi:nil="true"/>
      </PROPERTY>
      <PROPERTY>
        <NAME>LOCAL_PREPROCESSOR_NAME08</NAME>
        <VALUE xsi:nil="true"/>
      </PROPERTY>
      <PROPERTY>
        <NAME>LOCAL_PREPROCESSOR_NAME09</NAME>
        <VALUE xsi:nil="true"/>
      </PROPERTY>
      <PROPERTY>
        <NAME>LOCAL_PREPROCESSOR_NAME10</NAME>
        <VALUE xsi:nil="true"/>
      </PROPERTY>
      <PROPERTY>
        <NAME>LOCAL_PREPROCESSOR_OPTIONS02</NAME>
        <VALUE xsi:nil="true"/>
      </PROPERTY>
      <PROPERTY>
        <NAME>LOCAL_PREPROCESSOR_OPTIONS03</NAME>
        <VALUE xsi:nil="true"/>
      </PROPERTY>
      <PROPERTY>
        <NAME>LOCAL_PREPROCESSOR_OPTIONS04</NAME>
        <VALUE xsi:nil="true"/>
      </PROPERTY>
      <PROPERTY>
        <NAME>LOCAL_PREPROCESSOR_OPTIONS05</NAME>
        <VALUE xsi:nil="true"/>
      </PROPERTY>
      <PROPERTY>
        <NAME>LOCAL_PREPROCESSOR_OPTIONS06</NAME>
        <VALUE xsi:nil="true"/>
      </PROPERTY>
      <PROPERTY>
        <NAME>LOCAL_PREPROCESSOR_OPTIONS07</NAME>
        <VALUE xsi:nil="true"/>
      </PROPERTY>
      <PROPERTY>
        <NAME>LOCAL_PREPROCESSOR_OPTIONS08</NAME>
        <VALUE xsi:nil="true"/>
      </PROPERTY>
      <PROPERTY>
        <NAME>LOCAL_PREPROCESSOR_OPTIONS09</NAME>
        <VALUE xsi:nil="true"/>
      </PROPERTY>
      <PROPERTY>
        <NAME>LOCAL_PREPROCESSOR_OPTIONS10</NAME>
        <VALUE xsi:nil="true"/>
      </PROPERTY>
      <PROPERTY>
        <NAME>LOCAL_PREPROCESSOR_OUTPUT_FILE_NAME02</NAME>
        <VALUE xsi:nil="true"/>
      </PROPERTY>
      <PROPERTY>
        <NAME>LOCAL_PREPROCESSOR_OUTPUT_FILE_NAME03</NAME>
        <VALUE xsi:nil="true"/>
      </PROPERTY>
      <PROPERTY>
        <NAME>LOCAL_PREPROCESSOR_OUTPUT_FILE_NAME04</NAME>
        <VALUE xsi:nil="true"/>
      </PROPERTY>
      <PROPERTY>
        <NAME>LOCAL_PREPROCESSOR_OUTPUT_FILE_NAME05</NAME>
        <VALUE xsi:nil="true"/>
      </PROPERTY>
      <PROPERTY>
        <NAME>LOCAL_PREPROCESSOR_OUTPUT_FILE_NAME06</NAME>
        <VALUE xsi:nil="true"/>
      </PROPERTY>
      <PROPERTY>
        <NAME>LOCAL_PREPROCESSOR_OUTPUT_FILE_NAME07</NAME>
        <VALUE xsi:nil="true"/>
      </PROPERTY>
      <PROPERTY>
        <NAME>LOCAL_PREPROCESSOR_OUTPUT_FILE_NAME08</NAME>
        <VALUE xsi:nil="true"/>
      </PROPERTY>
      <PROPERTY>
        <NAME>LOCAL_PREPROCESSOR_OUTPUT_FILE_NAME09</NAME>
        <VALUE xsi:nil="true"/>
      </PROPERTY>
      <PROPERTY>
        <NAME>LOCAL_PREPROCESSOR_OUTPUT_FILE_NAME10</NAME>
        <VALUE xsi:nil="true"/>
      </PROPERTY>
      <PROPERTY>
        <NAME>LOCAL_PREPROCESSOR_SUPPORT_ERRFDBK02</NAME>
        <VALUE xsi:nil="true"/>
      </PROPERTY>
      <PROPERTY>
        <NAME>LOCAL_PREPROCESSOR_SUPPORT_ERRFDBK03</NAME>
        <VALUE xsi:nil="true"/>
      </PROPERTY>
      <PROPERTY>
        <NAME>LOCAL_PREPROCESSOR_SUPPORT_ERRFDBK04</NAME>
        <VALUE xsi:nil="true"/>
      </PROPERTY>
      <PROPERTY>
        <NAME>LOCAL_PREPROCESSOR_SUPPORT_ERRFDBK05</NAME>
        <VALUE xsi:nil="true"/>
      </PROPERTY>
      <PROPERTY>
        <NAME>LOCAL_PREPROCESSOR_SUPPORT_ERRFDBK06</NAME>
        <VALUE xsi:nil="true"/>
      </PROPERTY>
      <PROPERTY>
        <NAME>LOCAL_PREPROCESSOR_SUPPORT_ERRFDBK07</NAME>
        <VALUE xsi:nil="true"/>
      </PROPERTY>
      <PROPERTY>
        <NAME>LOCAL_PREPROCESSOR_SUPPORT_ERRFDBK08</NAME>
        <VALUE xsi:nil="true"/>
      </PROPERTY>
      <PROPERTY>
        <NAME>LOCAL_PREPROCESSOR_SUPPORT_ERRFDBK09</NAME>
        <VALUE xsi:nil="true"/>
      </PROPERTY>
      <PROPERTY>
        <NAME>LOCAL_PREPROCESSOR_SUPPORT_ERRFDBK10</NAME>
        <VALUE xsi:nil="true"/>
      </PROPERTY>
      <PROPERTY>
        <NAME>LOCAL_PREPROCESSOR_XML_LOCATION02</NAME>
        <VALUE xsi:nil="true"/>
      </PROPERTY>
      <PROPERTY>
        <NAME>LOCAL_PREPROCESSOR_XML_LOCATION03</NAME>
        <VALUE xsi:nil="true"/>
      </PROPERTY>
      <PROPERTY>
        <NAME>LOCAL_PREPROCESSOR_XML_LOCATION04</NAME>
        <VALUE xsi:nil="true"/>
      </PROPERTY>
      <PROPERTY>
        <NAME>LOCAL_PREPROCESSOR_XML_LOCATION05</NAME>
        <VALUE xsi:nil="true"/>
      </PROPERTY>
      <PROPERTY>
        <NAME>LOCAL_PREPROCESSOR_XML_LOCATION06</NAME>
        <VALUE xsi:nil="true"/>
      </PROPERTY>
      <PROPERTY>
        <NAME>LOCAL_PREPROCESSOR_XML_LOCATION07</NAME>
        <VALUE xsi:nil="true"/>
      </PROPERTY>
      <PROPERTY>
        <NAME>LOCAL_PREPROCESSOR_XML_LOCATION08</NAME>
        <VALUE xsi:nil="true"/>
      </PROPERTY>
      <PROPERTY>
        <NAME>LOCAL_PREPROCESSOR_XML_LOCATION09</NAME>
        <VALUE xsi:nil="true"/>
      </PROPERTY>
      <PROPERTY>
        <NAME>LOCAL_PREPROCESSOR_XML_LOCATION10</NAME>
        <VALUE xsi:nil="true"/>
      </PROPERTY>
      <PROPERTY>
        <NAME>LOCAL_PREPROCESSOR_ENVIRONMENT_VARIABLES02</NAME>
        <VALUE xsi:nil="true"/>
      </PROPERTY>
      <PROPERTY>
        <NAME>LOCAL_PREPROCESSOR_ENVIRONMENT_VARIABLES03</NAME>
        <VALUE xsi:nil="true"/>
      </PROPERTY>
      <PROPERTY>
        <NAME>LOCAL_PREPROCESSOR_ENVIRONMENT_VARIABLES04</NAME>
        <VALUE xsi:nil="true"/>
      </PROPERTY>
      <PROPERTY>
        <NAME>LOCAL_PREPROCESSOR_ENVIRONMENT_VARIABLES05</NAME>
        <VALUE xsi:nil="true"/>
      </PROPERTY>
      <PROPERTY>
        <NAME>LOCAL_PREPROCESSOR_ENVIRONMENT_VARIABLES06</NAME>
        <VALUE xsi:nil="true"/>
      </PROPERTY>
      <PROPERTY>
        <NAME>LOCAL_PREPROCESSOR_ENVIRONMENT_VARIABLES07</NAME>
        <VALUE xsi:nil="true"/>
      </PROPERTY>
      <PROPERTY>
        <NAME>LOCAL_PREPROCESSOR_ENVIRONMENT_VARIABLES08</NAME>
        <VALUE xsi:nil="true"/>
      </PROPERTY>
      <PROPERTY>
        <NAME>LOCAL_PREPROCESSOR_ENVIRONMENT_VARIABLES09</NAME>
        <VALUE xsi:nil="true"/>
      </PROPERTY>
      <PROPERTY>
        <NAME>LOCAL_PREPROCESSOR_ENVIRONMENT_VARIABLES10</NAME>
        <VALUE xsi:nil="true"/>
      </PROPERTY>
      <PROPERTY>
        <NAME>LOCAL_PREPROCESSOR_IS_ACTIVE02</NAME>
        <VALUE xsi:nil="true"/>
      </PROPERTY>
      <PROPERTY>
        <NAME>LOCAL_PREPROCESSOR_IS_ACTIVE03</NAME>
        <VALUE xsi:nil="true"/>
      </PROPERTY>
      <PROPERTY>
        <NAME>LOCAL_PREPROCESSOR_IS_ACTIVE04</NAME>
        <VALUE xsi:nil="true"/>
      </PROPERTY>
      <PROPERTY>
        <NAME>LOCAL_PREPROCESSOR_IS_ACTIVE05</NAME>
        <VALUE xsi:nil="true"/>
      </PROPERTY>
      <PROPERTY>
        <NAME>LOCAL_PREPROCESSOR_IS_ACTIVE06</NAME>
        <VALUE xsi:nil="true"/>
      </PROPERTY>
      <PROPERTY>
        <NAME>LOCAL_PREPROCESSOR_IS_ACTIVE07</NAME>
        <VALUE xsi:nil="true"/>
      </PROPERTY>
      <PROPERTY>
        <NAME>LOCAL_PREPROCESSOR_IS_ACTIVE08</NAME>
        <VALUE xsi:nil="true"/>
      </PROPERTY>
      <PROPERTY>
        <NAME>LOCAL_PREPROCESSOR_IS_ACTIVE09</NAME>
        <VALUE xsi:nil="true"/>
      </PROPERTY>
      <PROPERTY>
        <NAME>LOCAL_PREPROCESSOR_IS_ACTIVE10</NAME>
        <VALUE xsi:nil="true"/>
      </PROPERTY>
      <PROPERTY>
        <NAME>USE_LOCAL_PREPROCESSORS</NAME>
        <VALUE xsi:nil="true"/>
      </PROPERTY>
      <PROPERTY>
        <NAME>USE_EXTENSION_PREPROCESSOR</NAME>
        <VALUE xsi:nil="true"/>
      </PROPERTY>
      <PROPERTY>
        <NAME>USE_REMOTE_PREPROCESSORS</NAME>
        <VALUE xsi:nil="true"/>
      </PROPERTY>
      <PROPERTY>
        <NAME>SCRIPT_INVOKING_PREPROCESSOR</NAME>
        <VALUE xsi:nil="true"/>
      </PROPERTY>
      <PROPERTY>
        <NAME>PREPROCESSOR_OUTPUT_LOCATION</NAME>
        <VALUE xsi:nil="true"/>
      </PROPERTY>
      <PROPERTY>
        <NAME>PREPROCESSOR_PARAMETERS</NAME>
        <VALUE xsi:nil="true"/>
      </PROPERTY>
      <PROPERTY>
        <NAME>PREPROCESSOR_HIGH_LEVEL_QUALIFIER</NAME>
        <VALUE xsi:nil="true"/>
      </PROPERTY>
      <PROPERTY>
        <NAME>EXTENSION_PREPROCESSOR_ID</NAME>
        <VALUE xsi:nil="true"/>
      </PROPERTY>
      <PROPERTY>
        <NAME>LOCAL_INCLUDE_LIBRARIES</NAME>
        <VALUE xsi:nil="true"/>
      </PROPERTY>
      <PROPERTY>
        <NAME>REMOTE_INCLUDE_LIBRARIES</NAME>
        <VALUE xsi:nil="true"/>
      </PROPERTY>
      <PROPERTY>
        <NAME>REMOTE_INCLUDE_LIBRARIES_SYSTEM</NAME>
        <VALUE xsi:nil="true"/>
      </PROPERTY>
      <PROPERTY>
        <NAME>PROGRAM_LOOKUP_PATH</NAME>
        <VALUE xsi:nil="true"/>
      </PROPERTY>
      <PROPERTY>
        <NAME>REMOTE_PROGRAM_LOOKUP_PATH</NAME>
        <VALUE xsi:nil="true"/>
      </PROPERTY>
      <PROPERTY>
        <NAME>REMOTE_PROGRAM_LOOKUP_PATH_SYSTEM</NAME>
        <VALUE xsi:nil="true"/>
      </PROPERTY>
    </CATEGORY-INSTANCE>
  </PROPERTY-GROUP>
</PROPERTY-GROUPS>
